might/__init__.py
might/allmight.py
might/amr_methods.py
might/assembly_methods.py
might/database_methods.py
might/kraken_methods.py
might/might.py
might/might_log.py
might/miscellaneous.py
mrsn_might-1.0.5.dist-info/LICENSE
mrsn_might-1.0.5.dist-info/METADATA
mrsn_might-1.0.5.dist-info/WHEEL
mrsn_might-1.0.5.dist-info/entry_points.txt
mrsn_might-1.0.5.dist-info/top_level.txt
mrsn_might-1.0.5.dist-info/RECORD
