Metadata-Version: 2.1
Name: mrsn-might
Version: 1.0.5
Summary: MIGHT: MRSN Integrated Genome Handling Tool for bacterial clinical isolates
Home-page: https://gitlab.com/mrsn-bio/might/
Author: Brendan Corey
Author-email: brendan.w.corey.ctr@mail.mil
License: GPLv3
Platform: UNKNOWN
Classifier: Programming Language :: Python :: 3
Classifier: License :: OSI Approved :: GNU General Public License v3 (GPLv3)
Requires-Python: >=3.4
